pylocuszoom/__init__.py
pylocuszoom/_plotter_utils.py
pylocuszoom/colors.py
pylocuszoom/config.py
pylocuszoom/ensembl.py
pylocuszoom/eqtl.py
pylocuszoom/exceptions.py
pylocuszoom/finemapping.py
pylocuszoom/forest.py
pylocuszoom/gene_track.py
pylocuszoom/labels.py
pylocuszoom/ld.py
pylocuszoom/loaders.py
pylocuszoom/logging.py
pylocuszoom/manhattan.py
pylocuszoom/manhattan_plotter.py
pylocuszoom/phewas.py
pylocuszoom/plotter.py
pylocuszoom/py.typed
pylocuszoom/qq.py
pylocuszoom/recombination.py
pylocuszoom/schemas.py
pylocuszoom/stats_plotter.py
pylocuszoom/utils.py
pylocuszoom/validation.py
pylocuszoom/backends/__init__.py
pylocuszoom/backends/base.py
pylocuszoom/backends/bokeh_backend.py
pylocuszoom/backends/hover.py
pylocuszoom/backends/matplotlib_backend.py
pylocuszoom/backends/plotly_backend.py
pylocuszoom/reference_data/__init__.py
pylocuszoom-1.1.2.dist-info/METADATA
pylocuszoom-1.1.2.dist-info/WHEEL
pylocuszoom-1.1.2.dist-info/licenses/LICENSE.md
pylocuszoom-1.1.2.dist-info/RECORD
