Metadata-Version: 2.4
Name: pylocuszoom
Version: 1.1.2
Summary: Publication-ready regional association plots with LD coloring, gene tracks, and recombination overlays
Project-URL: Homepage, https://github.com/michael-denyer/pylocuszoom
Project-URL: Documentation, https://github.com/michael-denyer/pylocuszoom#readme
Project-URL: Repository, https://github.com/michael-denyer/pylocuszoom
Author-email: Michael Denyer <code.denyer@gmail.com>
License-Expression: GPL-3.0-or-later
License-File: LICENSE.md
Keywords: genetics,gwas,locus-zoom,locuszoom,regional-plot,visualization
Classifier: Development Status :: 4 - Beta
Classifier: Intended Audience :: Science/Research
Classifier: License :: OSI Approved :: GNU General Public License v3 or later (GPLv3+)
Classifier: Programming Language :: Python :: 3
Classifier: Programming Language :: Python :: 3.10
Classifier: Programming Language :: Python :: 3.11
Classifier: Programming Language :: Python :: 3.12
Classifier: Topic :: Scientific/Engineering :: Bio-Informatics
Classifier: Topic :: Scientific/Engineering :: Visualization
Requires-Python: >=3.10
Requires-Dist: adjusttext>=0.8
Requires-Dist: bokeh>=3.8.2
Requires-Dist: colorcet>=3.0.0
Requires-Dist: kaleido>=0.2.0
Requires-Dist: loguru>=0.7.0
Requires-Dist: matplotlib>=3.5.0
Requires-Dist: numpy>=1.21.0
Requires-Dist: pandas>=1.4.0
Requires-Dist: plotly>=5.15.0
Requires-Dist: pydantic>=2.0.0
Requires-Dist: pyliftover>=0.4
Requires-Dist: requests>=2.25.0
Requires-Dist: tqdm>=4.60.0
Provides-Extra: all
Requires-Dist: pyspark>=3.0.0; extra == 'all'
Provides-Extra: dev
Requires-Dist: pytest-cov>=4.0.0; extra == 'dev'
Requires-Dist: pytest-randomly>=3.0.0; extra == 'dev'
Requires-Dist: pytest-xdist>=3.0.0; extra == 'dev'
Requires-Dist: pytest>=7.0.0; extra == 'dev'
Requires-Dist: ruff>=0.1.0; extra == 'dev'
Provides-Extra: spark
Requires-Dist: pyspark>=3.0.0; extra == 'spark'
